setup.py
lwt/__init__.py
lwt/args.py
lwt/processes.py
lwt/report.py
lwt.egg-info/PKG-INFO
lwt.egg-info/SOURCES.txt
lwt.egg-info/dependency_links.txt
lwt.egg-info/entry_points.txt
lwt.egg-info/top_level.txt