Metadata-Version: 1.1
Name: lwt
Version: 0.1.0
Summary: Extensible data structure traversal in the command line
Home-page: https://github.com/port-zero/lwt
Author: Veit Heller
Author-email: UNKNOWN
License: MIT
Download-URL: https://github.com/port-zero/lwt/tarball/0.1.0
Platform: UNKNOWN
